telemaster.py
telemaster-1.1.0.dist-info/licenses/LICENSE.txt
telemaster-1.1.0.dist-info/METADATA
telemaster-1.1.0.dist-info/WHEEL
telemaster-1.1.0.dist-info/top_level.txt
telemaster-1.1.0.dist-info/RECORD
