Metadata-Version: 2.4
Name: telemaster
Version: 1.1.0
Summary: Telemaster — easy Python library for logs management in Telegram.
Author: David Pim
License-File: LICENSE.txt
Dynamic: author
Dynamic: description
Dynamic: description-content-type
Dynamic: license-file
Dynamic: summary
